fringez/__init__.py
fringez/convert.py
fringez/fringe.py
fringez/metric.py
fringez/model.py
fringez/plot.py
fringez/utils.py
fringez-1.3.5.data/scripts/fringez-clean
fringez-1.3.5.data/scripts/fringez-download
fringez-1.3.5.data/scripts/fringez-generate
fringez-1.3.5.dist-info/LICENSE
fringez-1.3.5.dist-info/METADATA
fringez-1.3.5.dist-info/WHEEL
fringez-1.3.5.dist-info/top_level.txt
fringez-1.3.5.dist-info/RECORD
