Metadata-Version: 2.1
Name: fringez
Version: 1.3.5
Summary: Removing atmospheric fringes from ZTF i-band images
Home-page: https://github.com/MichaelMedford/fringez
Author: Michael Medford
Author-email: michaelmedford@berkeley.edu
License: MIT
Download-URL: https://github.com/MichaelMedford/fringez/tarball/1.3.5
Project-URL: Models, https://portal.nersc.gov/project/ptf/iband
Platform: UNKNOWN
Classifier: Intended Audience :: Science/Research
Classifier: Programming Language :: Python :: 3.5
Classifier: License :: OSI Approved :: MIT License
Classifier: Topic :: Scientific/Engineering :: Astronomy
Classifier: Operating System :: POSIX
Classifier: Operating System :: Unix
Classifier: Operating System :: MacOS
Requires-Python: >=3.5
Requires-Dist: astropy
Requires-Dist: joblib
Requires-Dist: numpy
Requires-Dist: matplotlib
Requires-Dist: scikit-learn
Requires-Dist: requests
Requires-Dist: wget
Requires-Dist: beautifulsoup4
